MANIFEST.in
setup.py
ygctools/__init__.py
ygctools/cmd.py
ygctools.egg-info/PKG-INFO
ygctools.egg-info/SOURCES.txt
ygctools.egg-info/dependency_links.txt
ygctools.egg-info/entry_points.txt
ygctools.egg-info/top_level.txt
ygctools/alitools/astyle
ygctools/alitools/docscope
ygctools/alitools/dotrace_csky
ygctools/alitools/dotrace_riscv
ygctools/alitools/duk
ygctools/alitools/kvdump
ygctools/alitools/lfs_extrator
ygctools/alitools/mini_adpcm_ffmpeg
ygctools/alitools/mklfs
ygctools/alitools/pyoc
ygctools/misc/misc_ygc.tar.gz